flask_kraken_wq/__init__.py
flask_kraken_wq/exmaple.py
flask_kraken_wq/q.py
flask_kraken_wq/work.py
flask_kraken_wq-2021.8.16.dist-info/METADATA
flask_kraken_wq-2021.8.16.dist-info/WHEEL
flask_kraken_wq-2021.8.16.dist-info/top_level.txt
flask_kraken_wq-2021.8.16.dist-info/RECORD
