Metadata-Version: 2.1
Name: flask-kraken-wq
Version: 2021.8.16
Summary: flask sync run 
Home-page: https://github.com/kraken-cloud/kraken
Author: wei.fu
Author-email: mefuwei@163.com
License: UNKNOWN
Platform: UNKNOWN
Classifier: Programming Language :: Python :: 3
Classifier: License :: OSI Approved :: MIT License
Classifier: Operating System :: OS Independent
Requires-Dist: redis
